hh_jira_mcp_server/__init__.py
hh_jira_mcp_server/server.py
hh_jira_mcp_server/utils.py
mseep_hh_jira_mcp_server-0.1.4.dist-info/METADATA
mseep_hh_jira_mcp_server-0.1.4.dist-info/WHEEL
mseep_hh_jira_mcp_server-0.1.4.dist-info/entry_points.txt
mseep_hh_jira_mcp_server-0.1.4.dist-info/top_level.txt
mseep_hh_jira_mcp_server-0.1.4.dist-info/RECORD
